cis_checks_2023_u1_2/__init__.py
cis_checks_2023_u1_2/_security_control_5.py
cis_checks_2023_u1_2/iam_control_1.py
cis_checks_2023_u1_2/logging_control_3.py
cis_checks_2023_u1_2/monitoring_control_4.py
cis_checks_2023_u1_2/networking_control_5.py
cis_checks_2023_u1_2/storage_control_2.py
cis_checks_2023_u1_2/utils.py
cis_checks_2023_u1_2-2.1.2.dist-info/METADATA
cis_checks_2023_u1_2-2.1.2.dist-info/WHEEL
cis_checks_2023_u1_2-2.1.2.dist-info/top_level.txt
cis_checks_2023_u1_2-2.1.2.dist-info/RECORD
