Metadata-Version: 2.1
Name: cis-checks-2023-u1-2
Version: 2.1.2
Summary: Provides AWS compliance details
Author-email: Dheeraj Banodha <dheeraj.banodha@impetus.com>, Ravish Sharma <ravish.sharma@impetus.com>
Classifier: Programming Language :: Python :: 3
Classifier: Operating System :: OS Independent
Requires-Python: >=3.7
Requires-Dist: boto3
Requires-Dist: pytz
